LICENSE
README.md
setup.cfg
setup.py
medux_online/__init__.py
medux_online/asgi.py
medux_online/hosts.py
medux_online/settings.py
medux_online/urls.py
medux_online/wsgi.py
medux_online.egg-info/PKG-INFO
medux_online.egg-info/SOURCES.txt
medux_online.egg-info/dependency_links.txt
medux_online.egg-info/requires.txt
medux_online.egg-info/top_level.txt
medux_online.egg-info/zip-safe
medux_online/core/__init__.py
medux_online/core/admin.py
medux_online/core/apps.py
medux_online/core/forms.py
medux_online/core/menus.py
medux_online/core/middleware.py
medux_online/core/mixins.py
medux_online/core/models.py
medux_online/core/tools.py
medux_online/core/urls.py
medux_online/core/views.py
medux_online/core/api/__init__.py
medux_online/core/api/interfaces.py
medux_online/core/components/__init__.py
medux_online/core/components/preferences.py
medux_online/core/components/scope_switcher.py
medux_online/core/components/settings_item.py
medux_online/core/components/core/__init__.py
medux_online/core/components/core/nullable_switch_button.py
medux_online/core/migrations/__init__.py
medux_online/core/tests/__init__.py
medux_online/core/tests/test_views.py
medux_online/plugins/__init__.py
medux_online/plugins/homepage/__init__.py
medux_online/plugins/homepage/admin.py
medux_online/plugins/homepage/api.py
medux_online/plugins/homepage/apps.py
medux_online/plugins/homepage/forms.py
medux_online/plugins/homepage/hosts.py
medux_online/plugins/homepage/models.py
medux_online/plugins/homepage/root_urls.py
medux_online/plugins/homepage/urls.py
medux_online/plugins/homepage/components/__init__.py
medux_online/plugins/homepage/components/block_edit.py
medux_online/plugins/homepage/fixtures/__init__.py
medux_online/plugins/homepage/migrations/__init__.py
medux_online/plugins/homepage/templatetags/__init__.py
medux_online/plugins/homepage/tests/__init__.py
medux_online/plugins/homepage/tests/test_views.py
medux_online/plugins/homepage/views/__init__.py
medux_online/plugins/homepage/views/common.py
medux_online/plugins/prescriptions/__init__.py
medux_online/plugins/prescriptions/admin.py
medux_online/plugins/prescriptions/apps.py
medux_online/plugins/prescriptions/forms.py
