Metadata-Version: 2.1
Name: medux-online
Version: 0.0.2
Summary: "MedUX Online - Website tools for MedUX"
Home-page: https://medux.at/
Author: Christian González
Author-email: christian.gonzalez@nerdocs.at
License: AGPLv3+
Platform: UNKNOWN
Classifier: Development Status :: 2 - Pre-Alpha
Classifier: Environment :: Web Environment
Classifier: Framework :: Django :: 4.0
Classifier: Intended Audience :: Developers
Classifier: License :: OSI Approved :: GNU Affero General Public License v3 or later (AGPLv3+)
Classifier: Natural Language :: English
Classifier: Operating System :: OS Independent
Classifier: Programming Language :: Python :: 3 :: Only
Classifier: Programming Language :: Python :: 3.10
Classifier: Programming Language :: JavaScript
Classifier: Topic :: Internet :: WWW/HTTP
Classifier: Topic :: Internet :: WWW/HTTP :: Dynamic Content
Requires-Python: >=3.10
Provides-Extra: dev
License-File: LICENSE
